{
  "Arryadia.ar": {},
  "AlJazeera.ar": {},
  "6ter.fr": {},
  "Arte.fr": {},
  "DAZN.fr": {},
  "DAZN2.fr": {},
  "DAZNLigue1.fr": {},
  "DAZNLigue1M1.fr": {},
  "DAZNLigue1M2.fr": {},
  "DAZNLigue1M3.fr": {},
  "DAZNLigue1M4.fr": {},
  "DAZNLigue1M5.fr": {},
  "DAZNLigue1M6.fr": {},
  "DAZNLigue1M7.fr": {},
  "DAZNLigue1M8.fr": {},
  "beINSPORTS1.fr": {},
  "beINSPORTS2.fr": {},
  "beINSPORTS3.fr": {},
  "beINSPORTSMAX10.fr": {},
  "beINSPORTSMAX4.fr": {},
  "beINSPORTSMAX5.fr": {},
  "beINSPORTSMAX6.fr": {},
  "beINSPORTSMAX7.fr": {},
  "beINSPORTSMAX8.fr": {},
  "beINSPORTSMAX9.fr": {},
  "ElevenSports1FR.be": {"name":"Eleven sport 1"},
  "ElevenSports2FR.be": {"name":"Eleven sport 2"},
  "ElevenSports3FR.be": {"name":"Eleven sport 3"},
  "VOOSportWorld1.be": {"name":"Voo sport world 1"},
  "VOOSportWorld2.be": {"name":"Voo sport world 2"},
  "VOOSportWorld3.be": {"name":"Voo sport world 3"},
  "BFMTV.fr": {},
  "C8.fr": {},
  "01TV.fr": {},
  "MyZenTV.fr":{},
  "CanalPlus.fr": {},
  "CanalPlusBoxOffice.fr": {},
  "CanalPlusCinema.fr": {},
  "CanalPlusFamily.fr": {},
  "CanalPlusSeries.fr": {},
  "CanalPlusSport.fr": {},
  "CinePlusClassic.fr": {},
  "CinePlusEmotion.fr": {},
  "CinePlusFamiz.fr": {},
  "CinePlusFrisson.fr": {},
  "CinePlusPremier.fr": {},
  "CanalPlusDocs.fr": {},
  "CNews.fr": {},
  "ComediePlus.fr": {},
  "CStar.fr": {},
  "DiscoveryChannel.fr": {},
  "DiscoveryInvestigation.fr": {},
  "DiscoveryScience.fr": {},
  "Euronews.fr": {},
  "Eurosport1.fr": {},
  "Eurosport2.fr": {},
  "France2.fr": {"priority":["Orange"]},
  "France24.fr": {},
  "France3.fr": {},
  "France4.fr": {},
  "France5.fr": {},
  "FranceInfo.fr": {},
  "TF1SeriesFilms.fr": {},
  "Histoire.fr": {},
  "InfosportPlus.fr": {},
  "LEquipe21.fr": {"name":"Equipe 21"},
  "LaChaineParlementaire.fr": {},
  "LaDeux.be": {},
  "LaTrois.be": {},
  "LaUne.be": {},
  "Be1.be": {},
  "BeCine.be": {},
  "LCI.fr": {},
  "M6.fr": {"name":"m6"},
  "NatGeoWild.fr": {},
  "NationalGeographic.fr": {},
  "NRJ12.fr": {},
  "NT1.fr": {"name":"tfx"},
  "Numero23.fr": {"name":"rmc story"},
  "OCSMax.fr": {},
  "ParisPremiere.fr": {},
  "PlanetePlus.fr": {},
  "PlaneteAction.fr": {},
  "PLANETEJustice.fr": {},
  "RMC.fr": {},
  "RMCDecouverte.fr": {},
  "RTLTVI.be": {},
  "RTSDeux.ch": {},
  "RTSUn.ch": {},
  "ScienceEtVieTV.fr": {"name": "science&vie"},
  "Seasons.fr": {},
  "RMCSport1.fr": {"name": "rmc sport 1"},
  "RMCSport2.fr": {"name": "rmc sport 2"},
  "Syfy.fr": {},
  "TF1.fr": {},
  "TMC.fr": {},
  "TouteHistoire.fr": {},
  "TV5Monde.fr": {},
  "TV5MondeAfrique.fr": {},
  "TV5MondeEurope.fr": {},
  "UshuaiaTV.fr": {},
  "Voyage.fr": {},
  "W9.fr": {},
  "CanalPlusGrandEcran.fr": {"name":"canal Plus Grand ecran"},
  "CanalPlusSport360.fr": {"name":"canal Plus 360"},
  "CanalPlusFoot.fr": {},
  "CanalPlusMotoGP.fr": {},
  "CanalPlusFormula1.fr": {"name": "canal Plus F1"},
  "CanalPlusPremierLeague.fr": {"name": "canal Plus PL"},
  "CanalPlusSport1.af": {"name": "canal Plus Sport1 afrique"},
  "CanalPlusSport2.af": {"name": "canal Plus Sport2 afrique"},
  "CanalPlusSport3.af": {"name": "canal Plus Sport3 afrique"},
  "CanalPlusSport4.af": {"name": "canal Plus Sport4 afrique"},
  "CanalPlusSport5.af": {"name": "canal Plus Sport5 afrique"}
}
